LICENSE.txt
MANIFEST.in
setup.py
doc/Makefile
doc/conf.py
doc/index.rst
doc/installation.rst
doc/introduction.rst
doc/model.rst
doc/persistence.rst
doc/recipes.rst
doc/unified_execution.rst
railroadtracks.egg-info/PKG-INFO
railroadtracks.egg-info/SOURCES.txt
railroadtracks.egg-info/dependency_links.txt
railroadtracks.egg-info/requires.txt
railroadtracks.egg-info/top_level.txt
src/EF204940.fa
src/__init__.py
src/cache.sql
src/core.py
src/ef204940.gff
src/ef204940.gtf
src/environment.py
src/hortator.py
src/ipython.py
src/rnaseq.py
src/unifex.py
src/easy/__init__.py
src/easy/execution.py
src/easy/qsub.py
src/easy/taskgraph.py
src/easy/tasks.py
src/easy/tasksetgraph.py
src/model/__init__.py
src/model/aligners.py
src/model/deseq.R
src/model/deseq2.R
src/model/diffexp.py
src/model/ebseq.R
src/model/edger.R
src/model/featurecount.R
src/model/files.py
src/model/limmavoom.R
src/model/misc.py
src/model/quantify.py
src/model/simulate.py
src/templates/assetset_view.html
src/templates/project_view_activities.html
src/templates/project_view_results.html
src/templates/project_view_storage.html
src/templates/task_view.html
src/test/__init__.py
src/test/test_core.py
src/test/test_easy.py
src/test/test_easy_tasksetgraph.py
src/test/test_environment.py
src/test/test_hortator.py
src/test/test_model.py
src/test/test_qsub.py
src/test/test_recipe.py
src/test/test_unifex.py