Metadata-Version: 1.0
Name: railroadtracks
Version: 0.4.0
Summary: Framework to connect computional steps with an emphasis on RNA-Seq
Home-page: https://github.com/Novartis/railroadtracks
Author: Laurent Gautier
Author-email: laurent.gautier@novartis.com
License: License :: OSI Approved :: Apache Software License
Platform: UNKNOWN
